{
    "schema":  "musu.single_machine_smoke_evidence.v1",
    "ok":  true,
    "version":  "1.15.0-rc.1",
    "git_commit":  "bd36815a838aa7e5d76426ddf5e09b7da70d9b71",
    "smoke_run_id":  "20260605_025339",
    "started_at":  "2026-06-05T02:53:39.9244114+09:00",
    "completed_at":  "2026-06-05T02:54:04.8246016+09:00",
    "machine":  "HUGH_SECOND",
    "dashboard_base_url":  "http://127.0.0.1:3001",
    "dashboard_base_url_source":  "musu up.dashboard.reachable_url",
    "dashboard_reachable_url":  "http://127.0.0.1:3001/app",
    "bridge_url":  "http://127.0.0.1:13047",
    "workspace_uri":  "file:///F:/workspace/musu-bee",
    "doctor_overall":  "warn",
    "dashboard_doctor_overall":  "ok",
    "device_node_count":  2,
    "dashboard_task_id":  "ca28ea07-d681-466a-9554-cd985a286dd3",
    "dashboard_task_status":  "done",
    "dashboard_task_poll_error_count":  0,
    "dashboard_task_poll_last_error":  null,
    "expected_dashboard_output":  "MUSU_RELEASE_SMOKE_OK_20260605_025339",
    "dashboard_output":  "MUSU_RELEASE_SMOKE_OK_20260605_025339",
    "sse_status_code":  200,
    "sse_content_type":  "text/event-stream",
    "cli_route_checked":  true,
    "expected_cli_output":  "MUSU_CLI_ROUTE_OK_20260605_025339",
    "cli_route_output":  "??Sending task to local...\n??Task queued: bbdfc82a-2a80-45ac-a885-89bad51a6fdf\n??Waiting for task bbdfc82a-2a80-45ac-a885-89bad51a6fdf...\n??Task completed\nMUSU_CLI_ROUTE_OK_20260605_025339"
}
